[{"iob":0.597,"activity":0.0124,"bolussnooze":0,"basaliob":0.597,"netbasalinsulin":1.6,"hightempinsulin":1.6,"time":"2017-08-04T07:38:15.000Z"},{"iob":0.537,"activity":0.0119,"bolussnooze":0,"basaliob":0.537,"netbasalinsulin":1.6,"hightempinsulin":1.6,"time":"2017-08-04T07:43:15.000Z"},{"iob":0.48,"activity":0.0113,"bolussnooze":0,"basaliob":0.48,"netbasalinsulin":1.5,"hightempinsulin":1.5,"time":"2017-08-04T07:48:15.000Z"},{"iob":0.427,"activity":0.0107,"bolussnooze":0,"basaliob":0.427,"netbasalinsulin":1.45,"hightempinsulin":1.45,"time":"2017-08-04T07:53:15.000Z"},{"iob":0.376,"activity":0.0101,"bolussnooze":0,"basaliob":0.376,"netbasalinsulin":1.4,"hightempinsulin":1.4,"time":"2017-08-04T07:58:15.000Z"},{"iob":0.329,"activity":0.0094,"bolussnooze":0,"basaliob":0.329,"netbasalinsulin":1.4,"hightempinsulin":1.4,"time":"2017-08-04T08:03:15.000Z"},{"iob":0.285,"activity":0.0087,"bolussnooze":0,"basaliob":0.285,"netbasalinsulin":1.4,"hightempinsulin":1.4,"time":"2017-08-04T08:08:15.000Z"},{"iob":0.245,"activity":0.0081,"bolussnooze":0,"basaliob":0.245,"netbasalinsulin":1.4,"hightempinsulin":1.4,"time":"2017-08-04T08:13:15.000Z"},{"iob":0.208,"activity":0.0074,"bolussnooze":0,"basaliob":0.208,"netbasalinsulin":1.4,"hightempinsulin":1.4,"time":"2017-08-04T08:18:15.000Z"},{"iob":0.175,"activity":0.0067,"bolussnooze":0,"basaliob":0.175,"netbasalinsulin":1.4,"hightempinsulin":1.4,"time":"2017-08-04T08:23:15.000Z"},{"iob":0.145,"activity":0.006,"bolussnooze":0,"basaliob":0.145,"netbasalinsulin":1.4,"hightempinsulin":1.4,"time":"2017-08-04T08:28:15.000Z"},{"iob":0.118,"activity":0.0053,"bolussnooze":0,"basaliob":0.118,"netbasalinsulin":1.35,"hightempinsulin":1.35,"time":"2017-08-04T08:33:15.000Z"},{"iob":0.095,"activity":0.0046,"bolussnooze":0,"basaliob":0.095,"netbasalinsulin":1.25,"hightempinsulin":1.25,"time":"2017-08-04T08:38:15.000Z"},{"iob":0.076,"activity":0.0039,"bolussnooze":0,"basaliob":0.076,"netbasalinsulin":1.2,"hightempinsulin":1.2,"time":"2017-08-04T08:43:15.000Z"},{"iob":0.059,"activity":0.0033,"bolussnooze":0,"basaliob":0.059,"netbasalinsulin":1.1,"hightempinsulin":1.1,"time":"2017-08-04T08:48:15.000Z"},{"iob":0.045,"activity":0.0028,"bolussnooze":0,"basaliob":0.045,"netbasalinsulin":1,"hightempinsulin":1,"time":"2017-08-04T08:53:15.000Z"},{"iob":0.034,"activity":0.0023,"bolussnooze":0,"basaliob":0.034,"netbasalinsulin":0.9,"hightempinsulin":0.9,"time":"2017-08-04T08:58:15.000Z"},{"iob":0.025,"activity":0.0018,"bolussnooze":0,"basaliob":0.025,"netbasalinsulin":0.8,"hightempinsulin":0.8,"time":"2017-08-04T09:03:15.000Z"},{"iob":0.018,"activity":0.0014,"bolussnooze":0,"basaliob":0.018,"netbasalinsulin":0.7,"hightempinsulin":0.7,"time":"2017-08-04T09:08:15.000Z"},{"iob":0.013,"activity":0.0011,"bolussnooze":0,"basaliob":0.013,"netbasalinsulin":0.6,"hightempinsulin":0.6,"time":"2017-08-04T09:13:15.000Z"},{"iob":0.009,"activity":0.0008,"bolussnooze":0,"basaliob":0.009,"netbasalinsulin":0.5,"hightempinsulin":0.5,"time":"2017-08-04T09:18:15.000Z"},{"iob":0.006,"activity":0.0005,"bolussnooze":0,"basaliob":0.006,"netbasalinsulin":0.4,"hightempinsulin":0.4,"time":"2017-08-04T09:23:15.000Z"},{"iob":0.005,"activity":0.0004,"bolussnooze":0,"basaliob":0.005,"netbasalinsulin":0.25,"hightempinsulin":0.25,"time":"2017-08-04T09:28:15.000Z"},{"iob":0.003,"activity":0.0003,"bolussnooze":0,"basaliob":0.003,"netbasalinsulin":0.15,"hightempinsulin":0.15,"time":"2017-08-04T09:33:15.000Z"},{"iob":0.002,"activity":0.0002,"bolussnooze":0,"basaliob":0.002,"netbasalinsulin":0.1,"hightempinsulin":0.1,"time":"2017-08-04T09:38:15.000Z"},{"iob":0.002,"activity":0.0001,"bolussnooze":0,"basaliob":0.002,"netbasalinsulin":0.05,"hightempinsulin":0.05,"time":"2017-08-04T09:43:15.000Z"},{"iob":0.001,"activity":0.0001,"bolussnooze":0,"basaliob":0.001,"netbasalinsulin":0.05,"hightempinsulin":0.05,"time":"2017-08-04T09:48:15.000Z"},{"iob":0.001,"activity":0.0001,"bolussnooze":0,"basaliob":0.001,"netbasalinsulin":0.05,"hightempinsulin":0.05,"time":"2017-08-04T09:53:15.000Z"},{"iob":0,"activity":0.0001,"bolussnooze":0,"basaliob":0,"netbasalinsulin":0.05,"hightempinsulin":0.05,"time":"2017-08-04T09:58:15.000Z"},{"iob":0,"activity":0,"bolussnooze":0,"basaliob":0,"netbasalinsulin":0.05,"hightempinsulin":0.05,"time":"2017-08-04T10:03:15.000Z"},{"iob":0,"activity":0,"bolussnooze":0,"basaliob":0,"netbasalinsulin":0.05,"hightempinsulin":0.05,"time":"2017-08-04T10:08:15.000Z"},{"iob":0,"activity":0,"bolussnooze":0,"basaliob":0,"netbasalinsulin":0,"hightempinsulin":0,"time":"2017-08-04T10:13:15.000Z"},{"iob":0,"activity":0,"bolussnooze":0,"basaliob":0,"netbasalinsulin":0,"hightempinsulin":0,"time":"2017-08-04T10:18:15.000Z"},{"iob":0,"activity":0,"bolussnooze":0,"basaliob":0,"netbasalinsulin":0,"hightempinsulin":0,"time":"2017-08-04T10:23:15.000Z"},{"iob":0,"activity":0,"bolussnooze":0,"basaliob":0,"netbasalinsulin":0,"hightempinsulin":0,"time":"2017-08-04T10:28:15.000Z"},{"iob":0,"activity":0,"bolussnooze":0,"basaliob":0,"netbasalinsulin":0,"hightempinsulin":0,"time":"2017-08-04T10:33:15.000Z"},{"iob":0,"activity":0,"bolussnooze":0,"basaliob":0,"netbasalinsulin":0,"hightempinsulin":0,"time":"2017-08-04T10:38:15.000Z"},{"iob":0,"activity":0,"bolussnooze":0,"basaliob":0,"netbasalinsulin":0,"hightempinsulin":0,"time":"2017-08-04T10:43:15.000Z"},{"iob":0,"activity":0,"bolussnooze":0,"basaliob":0,"netbasalinsulin":0,"hightempinsulin":0,"time":"2017-08-04T10:48:15.000Z"},{"iob":0,"activity":0,"bolussnooze":0,"basaliob":0,"netbasalinsulin":0,"hightempinsulin":0,"time":"2017-08-04T10:53:15.000Z"},{"iob":0,"activity":0,"bolussnooze":0,"basaliob":0,"netbasalinsulin":0,"hightempinsulin":0,"time":"2017-08-04T10:58:15.000Z"},{"iob":0,"activity":0,"bolussnooze":0,"basaliob":0,"netbasalinsulin":0,"hightempinsulin":0,"time":"2017-08-04T11:03:15.000Z"}]
