[{"iob":0.701,"activity":0.0123,"bolussnooze":0,"basaliob":0.701,"netbasalinsulin":1.6,"hightempinsulin":1.7,"time":"2017-06-08T05:33:29.000Z"},{"iob":0.541,"activity":0.012,"bolussnooze":0,"basaliob":0.541,"netbasalinsulin":1.5,"hightempinsulin":1.7,"time":"2017-06-08T05:38:29.000Z"},{"iob":0.335,"activity":0.0113,"bolussnooze":0,"basaliob":0.335,"netbasalinsulin":1.35,"hightempinsulin":1.7,"time":"2017-06-08T05:43:29.000Z"},{"iob":0.182,"activity":0.0105,"bolussnooze":0,"basaliob":0.182,"netbasalinsulin":1.25,"hightempinsulin":1.7,"time":"2017-06-08T05:48:29.000Z"},{"iob":0.034,"activity":0.0096,"bolussnooze":0,"basaliob":0.034,"netbasalinsulin":1.15,"hightempinsulin":1.7,"time":"2017-06-08T05:53:29.000Z"},{"iob":-0.109,"activity":0.0086,"bolussnooze":0,"basaliob":-0.109,"netbasalinsulin":1.05,"hightempinsulin":1.7,"time":"2017-06-08T05:58:29.000Z"},{"iob":-0.197,"activity":0.0076,"bolussnooze":0,"basaliob":-0.197,"netbasalinsulin":1,"hightempinsulin":1.7,"time":"2017-06-08T06:03:29.000Z"},{"iob":-0.23,"activity":0.0066,"bolussnooze":0,"basaliob":-0.23,"netbasalinsulin":0.95,"hightempinsulin":1.65,"time":"2017-06-08T06:08:29.000Z"},{"iob":-0.257,"activity":0.0055,"bolussnooze":0,"basaliob":-0.257,"netbasalinsulin":0.9,"hightempinsulin":1.6,"time":"2017-06-08T06:13:29.000Z"},{"iob":-0.28,"activity":0.0046,"bolussnooze":0,"basaliob":-0.28,"netbasalinsulin":0.85,"hightempinsulin":1.55,"time":"2017-06-08T06:18:29.000Z"},{"iob":-0.298,"activity":0.0036,"bolussnooze":0,"basaliob":-0.298,"netbasalinsulin":0.75,"hightempinsulin":1.45,"time":"2017-06-08T06:23:29.000Z"},{"iob":-0.312,"activity":0.0027,"bolussnooze":0,"basaliob":-0.312,"netbasalinsulin":0.7,"hightempinsulin":1.4,"time":"2017-06-08T06:28:29.000Z"},{"iob":-0.321,"activity":0.0018,"bolussnooze":0,"basaliob":-0.321,"netbasalinsulin":0.6,"hightempinsulin":1.3,"time":"2017-06-08T06:33:29.000Z"},{"iob":-0.324,"activity":0.0007,"bolussnooze":0,"basaliob":-0.324,"netbasalinsulin":0.55,"hightempinsulin":1.25,"time":"2017-06-08T06:38:29.000Z"},{"iob":-0.322,"activity":-0.0004,"bolussnooze":0,"basaliob":-0.322,"netbasalinsulin":0.5,"hightempinsulin":1.2,"time":"2017-06-08T06:43:29.000Z"},{"iob":-0.315,"activity":-0.0015,"bolussnooze":0,"basaliob":-0.315,"netbasalinsulin":0.45,"hightempinsulin":1.15,"time":"2017-06-08T06:48:29.000Z"},{"iob":-0.303,"activity":-0.0024,"bolussnooze":0,"basaliob":-0.303,"netbasalinsulin":0.4,"hightempinsulin":1.1,"time":"2017-06-08T06:53:29.000Z"},{"iob":-0.287,"activity":-0.0031,"bolussnooze":0,"basaliob":-0.287,"netbasalinsulin":0.4,"hightempinsulin":1.1,"time":"2017-06-08T06:58:29.000Z"},{"iob":-0.269,"activity":-0.0037,"bolussnooze":0,"basaliob":-0.269,"netbasalinsulin":0.3,"hightempinsulin":1,"time":"2017-06-08T07:03:29.000Z"},{"iob":-0.248,"activity":-0.0041,"bolussnooze":0,"basaliob":-0.248,"netbasalinsulin":0.2,"hightempinsulin":0.9,"time":"2017-06-08T07:08:29.000Z"},{"iob":-0.227,"activity":-0.0043,"bolussnooze":0,"basaliob":-0.227,"netbasalinsulin":0.1,"hightempinsulin":0.8,"time":"2017-06-08T07:13:29.000Z"},{"iob":-0.205,"activity":-0.0043,"bolussnooze":0,"basaliob":-0.205,"netbasalinsulin":-0.1,"hightempinsulin":0.6,"time":"2017-06-08T07:18:29.000Z"},{"iob":-0.184,"activity":-0.0042,"bolussnooze":0,"basaliob":-0.184,"netbasalinsulin":-0.3,"hightempinsulin":0.4,"time":"2017-06-08T07:23:29.000Z"},{"iob":-0.164,"activity":-0.004,"bolussnooze":0,"basaliob":-0.164,"netbasalinsulin":-0.4,"hightempinsulin":0.3,"time":"2017-06-08T07:28:29.000Z"},{"iob":-0.145,"activity":-0.0038,"bolussnooze":0,"basaliob":-0.145,"netbasalinsulin":-0.4,"hightempinsulin":0.3,"time":"2017-06-08T07:33:29.000Z"},{"iob":-0.128,"activity":-0.0036,"bolussnooze":0,"basaliob":-0.128,"netbasalinsulin":-0.4,"hightempinsulin":0.3,"time":"2017-06-08T07:38:29.000Z"},{"iob":-0.111,"activity":-0.0034,"bolussnooze":0,"basaliob":-0.111,"netbasalinsulin":-0.4,"hightempinsulin":0.3,"time":"2017-06-08T07:43:29.000Z"},{"iob":-0.095,"activity":-0.0031,"bolussnooze":0,"basaliob":-0.095,"netbasalinsulin":-0.4,"hightempinsulin":0.3,"time":"2017-06-08T07:48:29.000Z"},{"iob":-0.08,"activity":-0.0029,"bolussnooze":0,"basaliob":-0.08,"netbasalinsulin":-0.4,"hightempinsulin":0.3,"time":"2017-06-08T07:53:29.000Z"},{"iob":-0.067,"activity":-0.0027,"bolussnooze":0,"basaliob":-0.067,"netbasalinsulin":-0.4,"hightempinsulin":0.3,"time":"2017-06-08T07:58:29.000Z"},{"iob":-0.054,"activity":-0.0025,"bolussnooze":0,"basaliob":-0.054,"netbasalinsulin":-0.4,"hightempinsulin":0.3,"time":"2017-06-08T08:03:29.000Z"},{"iob":-0.043,"activity":-0.0023,"bolussnooze":0,"basaliob":-0.043,"netbasalinsulin":-0.4,"hightempinsulin":0.3,"time":"2017-06-08T08:08:29.000Z"},{"iob":-0.032,"activity":-0.0021,"bolussnooze":0,"basaliob":-0.032,"netbasalinsulin":-0.45,"hightempinsulin":0.25,"time":"2017-06-08T08:13:29.000Z"},{"iob":-0.023,"activity":-0.0018,"bolussnooze":0,"basaliob":-0.023,"netbasalinsulin":-0.55,"hightempinsulin":0.15,"time":"2017-06-08T08:18:29.000Z"},{"iob":-0.015,"activity":-0.0015,"bolussnooze":0,"basaliob":-0.015,"netbasalinsulin":-0.65,"hightempinsulin":0.05,"time":"2017-06-08T08:23:29.000Z"},{"iob":-0.01,"activity":-0.0012,"bolussnooze":0,"basaliob":-0.01,"netbasalinsulin":-0.65,"hightempinsulin":0,"time":"2017-06-08T08:28:29.000Z"},{"iob":-0.005,"activity":-0.0008,"bolussnooze":0,"basaliob":-0.005,"netbasalinsulin":-0.6,"hightempinsulin":0,"time":"2017-06-08T08:33:29.000Z"},{"iob":-0.003,"activity":-0.0006,"bolussnooze":0,"basaliob":-0.003,"netbasalinsulin":-0.5,"hightempinsulin":0,"time":"2017-06-08T08:38:29.000Z"},{"iob":-0.001,"activity":-0.0003,"bolussnooze":0,"basaliob":-0.001,"netbasalinsulin":-0.35,"hightempinsulin":0,"time":"2017-06-08T08:43:29.000Z"},{"iob":0,"activity":-0.0002,"bolussnooze":0,"basaliob":0,"netbasalinsulin":-0.25,"hightempinsulin":0,"time":"2017-06-08T08:48:29.000Z"},{"iob":0,"activity":-0.0001,"bolussnooze":0,"basaliob":0,"netbasalinsulin":-0.15,"hightempinsulin":0,"time":"2017-06-08T08:53:29.000Z"},{"iob":0,"activity":0,"bolussnooze":0,"basaliob":0,"netbasalinsulin":-0.05,"hightempinsulin":0,"time":"2017-06-08T08:58:29.000Z"}]
