[{"iob":0.769,"activity":0.0145,"bolussnooze":0,"basaliob":0.098,"netbasalinsulin":-0.6,"hightempinsulin":0.25,"time":"2017-05-03T05:13:24.000Z"},{"iob":0.75,"activity":0.0139,"bolussnooze":0,"basaliob":0.163,"netbasalinsulin":-0.5,"hightempinsulin":0.3,"time":"2017-05-03T05:18:24.000Z"},{"iob":0.733,"activity":0.0133,"bolussnooze":0,"basaliob":0.224,"netbasalinsulin":-0.4,"hightempinsulin":0.35,"time":"2017-05-03T05:23:24.000Z"},{"iob":0.669,"activity":0.0128,"bolussnooze":0,"basaliob":0.232,"netbasalinsulin":-0.35,"hightempinsulin":0.35,"time":"2017-05-03T05:28:24.000Z"},{"iob":0.608,"activity":0.0122,"bolussnooze":0,"basaliob":0.238,"netbasalinsulin":-0.3,"hightempinsulin":0.35,"time":"2017-05-03T05:33:24.000Z"},{"iob":0.549,"activity":0.0117,"bolussnooze":0,"basaliob":0.241,"netbasalinsulin":-0.2,"hightempinsulin":0.35,"time":"2017-05-03T05:38:24.000Z"},{"iob":0.494,"activity":0.0111,"bolussnooze":0,"basaliob":0.241,"netbasalinsulin":-0.15,"hightempinsulin":0.35,"time":"2017-05-03T05:43:24.000Z"},{"iob":0.442,"activity":0.0105,"bolussnooze":0,"basaliob":0.239,"netbasalinsulin":-0.05,"hightempinsulin":0.35,"time":"2017-05-03T05:48:24.000Z"},{"iob":0.392,"activity":0.0098,"bolussnooze":0,"basaliob":0.235,"netbasalinsulin":0,"hightempinsulin":0.35,"time":"2017-05-03T05:53:24.000Z"},{"iob":0.347,"activity":0.0091,"bolussnooze":0,"basaliob":0.228,"netbasalinsulin":0.05,"hightempinsulin":0.35,"time":"2017-05-03T05:58:24.000Z"},{"iob":0.305,"activity":0.0084,"bolussnooze":0,"basaliob":0.22,"netbasalinsulin":0.1,"hightempinsulin":0.35,"time":"2017-05-03T06:03:24.000Z"},{"iob":0.266,"activity":0.0077,"bolussnooze":0,"basaliob":0.209,"netbasalinsulin":0.1,"hightempinsulin":0.35,"time":"2017-05-03T06:08:24.000Z"},{"iob":0.232,"activity":0.0069,"bolussnooze":0,"basaliob":0.197,"netbasalinsulin":0.1,"hightempinsulin":0.35,"time":"2017-05-03T06:13:24.000Z"},{"iob":0.202,"activity":0.006,"bolussnooze":0,"basaliob":0.184,"netbasalinsulin":0.15,"hightempinsulin":0.35,"time":"2017-05-03T06:18:24.000Z"},{"iob":0.177,"activity":0.005,"bolussnooze":0,"basaliob":0.17,"netbasalinsulin":0.15,"hightempinsulin":0.35,"time":"2017-05-03T06:23:24.000Z"},{"iob":0.156,"activity":0.004,"bolussnooze":0,"basaliob":0.156,"netbasalinsulin":0.15,"hightempinsulin":0.35,"time":"2017-05-03T06:28:24.000Z"},{"iob":0.142,"activity":0.0029,"bolussnooze":0,"basaliob":0.142,"netbasalinsulin":0.15,"hightempinsulin":0.35,"time":"2017-05-03T06:33:24.000Z"},{"iob":0.128,"activity":0.0028,"bolussnooze":0,"basaliob":0.128,"netbasalinsulin":0.15,"hightempinsulin":0.35,"time":"2017-05-03T06:38:24.000Z"},{"iob":0.115,"activity":0.0027,"bolussnooze":0,"basaliob":0.115,"netbasalinsulin":0.2,"hightempinsulin":0.35,"time":"2017-05-03T06:43:24.000Z"},{"iob":0.102,"activity":0.0026,"bolussnooze":0,"basaliob":0.102,"netbasalinsulin":0.2,"hightempinsulin":0.35,"time":"2017-05-03T06:48:24.000Z"},{"iob":0.09,"activity":0.0024,"bolussnooze":0,"basaliob":0.09,"netbasalinsulin":0.2,"hightempinsulin":0.35,"time":"2017-05-03T06:53:24.000Z"},{"iob":0.078,"activity":0.0023,"bolussnooze":0,"basaliob":0.078,"netbasalinsulin":0.2,"hightempinsulin":0.35,"time":"2017-05-03T06:58:24.000Z"},{"iob":0.067,"activity":0.0022,"bolussnooze":0,"basaliob":0.067,"netbasalinsulin":0.25,"hightempinsulin":0.35,"time":"2017-05-03T07:03:24.000Z"},{"iob":0.057,"activity":0.0021,"bolussnooze":0,"basaliob":0.057,"netbasalinsulin":0.3,"hightempinsulin":0.35,"time":"2017-05-03T07:08:24.000Z"},{"iob":0.047,"activity":0.0019,"bolussnooze":0,"basaliob":0.047,"netbasalinsulin":0.3,"hightempinsulin":0.35,"time":"2017-05-03T07:13:24.000Z"},{"iob":0.039,"activity":0.0017,"bolussnooze":0,"basaliob":0.039,"netbasalinsulin":0.3,"hightempinsulin":0.35,"time":"2017-05-03T07:18:24.000Z"},{"iob":0.031,"activity":0.0016,"bolussnooze":0,"basaliob":0.031,"netbasalinsulin":0.35,"hightempinsulin":0.35,"time":"2017-05-03T07:23:24.000Z"},{"iob":0.024,"activity":0.0014,"bolussnooze":0,"basaliob":0.024,"netbasalinsulin":0.35,"hightempinsulin":0.35,"time":"2017-05-03T07:28:24.000Z"},{"iob":0.018,"activity":0.0012,"bolussnooze":0,"basaliob":0.018,"netbasalinsulin":0.35,"hightempinsulin":0.35,"time":"2017-05-03T07:33:24.000Z"},{"iob":0.013,"activity":0.001,"bolussnooze":0,"basaliob":0.013,"netbasalinsulin":0.35,"hightempinsulin":0.35,"time":"2017-05-03T07:38:24.000Z"},{"iob":0.009,"activity":0.0008,"bolussnooze":0,"basaliob":0.009,"netbasalinsulin":0.35,"hightempinsulin":0.35,"time":"2017-05-03T07:43:24.000Z"},{"iob":0.005,"activity":0.0006,"bolussnooze":0,"basaliob":0.005,"netbasalinsulin":0.35,"hightempinsulin":0.35,"time":"2017-05-03T07:48:24.000Z"},{"iob":0.003,"activity":0.0005,"bolussnooze":0,"basaliob":0.003,"netbasalinsulin":0.3,"hightempinsulin":0.3,"time":"2017-05-03T07:53:24.000Z"},{"iob":0.002,"activity":0.0003,"bolussnooze":0,"basaliob":0.002,"netbasalinsulin":0.25,"hightempinsulin":0.25,"time":"2017-05-03T07:58:24.000Z"},{"iob":0.001,"activity":0.0002,"bolussnooze":0,"basaliob":0.001,"netbasalinsulin":0.2,"hightempinsulin":0.2,"time":"2017-05-03T08:03:24.000Z"},{"iob":0,"activity":0.0001,"bolussnooze":0,"basaliob":0,"netbasalinsulin":0.15,"hightempinsulin":0.15,"time":"2017-05-03T08:08:24.000Z"},{"iob":0,"activity":0,"bolussnooze":0,"basaliob":0,"netbasalinsulin":0.1,"hightempinsulin":0.1,"time":"2017-05-03T08:13:24.000Z"},{"iob":0,"activity":0,"bolussnooze":0,"basaliob":0,"netbasalinsulin":0.05,"hightempinsulin":0.05,"time":"2017-05-03T08:18:24.000Z"},{"iob":0,"activity":0,"bolussnooze":0,"basaliob":0,"netbasalinsulin":0,"hightempinsulin":0,"time":"2017-05-03T08:23:24.000Z"},{"iob":0,"activity":0,"bolussnooze":0,"basaliob":0,"netbasalinsulin":0,"hightempinsulin":0,"time":"2017-05-03T08:28:24.000Z"},{"iob":0,"activity":0,"bolussnooze":0,"basaliob":0,"netbasalinsulin":0,"hightempinsulin":0,"time":"2017-05-03T08:33:24.000Z"},{"iob":0,"activity":0,"bolussnooze":0,"basaliob":0,"netbasalinsulin":0,"hightempinsulin":0,"time":"2017-05-03T08:38:24.000Z"}]
