[{"iob":-0.38,"activity":-0.0126,"bolussnooze":0,"basaliob":-0.38,"netbasalinsulin":-1,"hightempinsulin":0.7,"time":"2017-09-09T09:34:26.000Z"},{"iob":-0.168,"activity":-0.0123,"bolussnooze":0,"basaliob":-0.168,"netbasalinsulin":-0.85,"hightempinsulin":0.85,"time":"2017-09-09T09:39:26.000Z"},{"iob":0.041,"activity":-0.0118,"bolussnooze":0,"basaliob":0.041,"netbasalinsulin":-0.75,"hightempinsulin":0.95,"time":"2017-09-09T09:44:26.000Z"},{"iob":0.196,"activity":-0.011,"bolussnooze":0,"basaliob":0.196,"netbasalinsulin":-0.7,"hightempinsulin":1,"time":"2017-09-09T09:49:26.000Z"},{"iob":0.247,"activity":-0.0101,"bolussnooze":0,"basaliob":0.247,"netbasalinsulin":-0.7,"hightempinsulin":1,"time":"2017-09-09T09:54:26.000Z"},{"iob":0.292,"activity":-0.0091,"bolussnooze":0,"basaliob":0.292,"netbasalinsulin":-0.7,"hightempinsulin":1,"time":"2017-09-09T09:59:26.000Z"},{"iob":0.333,"activity":-0.008,"bolussnooze":0,"basaliob":0.333,"netbasalinsulin":-0.75,"hightempinsulin":0.95,"time":"2017-09-09T10:04:26.000Z"},{"iob":0.366,"activity":-0.0068,"bolussnooze":0,"basaliob":0.366,"netbasalinsulin":-0.75,"hightempinsulin":0.95,"time":"2017-09-09T10:09:26.000Z"},{"iob":0.393,"activity":-0.0054,"bolussnooze":0,"basaliob":0.393,"netbasalinsulin":-0.75,"hightempinsulin":0.95,"time":"2017-09-09T10:14:26.000Z"},{"iob":0.413,"activity":-0.0039,"bolussnooze":0,"basaliob":0.413,"netbasalinsulin":-0.75,"hightempinsulin":0.95,"time":"2017-09-09T10:19:26.000Z"},{"iob":0.425,"activity":-0.0023,"bolussnooze":0,"basaliob":0.425,"netbasalinsulin":-0.75,"hightempinsulin":0.95,"time":"2017-09-09T10:24:26.000Z"},{"iob":0.428,"activity":-0.0007,"bolussnooze":0,"basaliob":0.428,"netbasalinsulin":-0.75,"hightempinsulin":0.95,"time":"2017-09-09T10:29:26.000Z"},{"iob":0.424,"activity":0.0008,"bolussnooze":0,"basaliob":0.424,"netbasalinsulin":-0.7,"hightempinsulin":0.95,"time":"2017-09-09T10:34:26.000Z"},{"iob":0.413,"activity":0.0022,"bolussnooze":0,"basaliob":0.413,"netbasalinsulin":-0.6,"hightempinsulin":0.95,"time":"2017-09-09T10:39:26.000Z"},{"iob":0.396,"activity":0.0033,"bolussnooze":0,"basaliob":0.396,"netbasalinsulin":-0.5,"hightempinsulin":0.95,"time":"2017-09-09T10:44:26.000Z"},{"iob":0.375,"activity":0.0041,"bolussnooze":0,"basaliob":0.375,"netbasalinsulin":-0.4,"hightempinsulin":0.95,"time":"2017-09-09T10:49:26.000Z"},{"iob":0.352,"activity":0.0047,"bolussnooze":0,"basaliob":0.352,"netbasalinsulin":-0.3,"hightempinsulin":0.95,"time":"2017-09-09T10:54:26.000Z"},{"iob":0.326,"activity":0.0051,"bolussnooze":0,"basaliob":0.326,"netbasalinsulin":-0.2,"hightempinsulin":0.95,"time":"2017-09-09T10:59:26.000Z"},{"iob":0.3,"activity":0.0052,"bolussnooze":0,"basaliob":0.3,"netbasalinsulin":-0.1,"hightempinsulin":0.95,"time":"2017-09-09T11:04:26.000Z"},{"iob":0.274,"activity":0.0052,"bolussnooze":0,"basaliob":0.274,"netbasalinsulin":-0.05,"hightempinsulin":0.95,"time":"2017-09-09T11:09:26.000Z"},{"iob":0.248,"activity":0.0052,"bolussnooze":0,"basaliob":0.248,"netbasalinsulin":0.05,"hightempinsulin":0.95,"time":"2017-09-09T11:14:26.000Z"},{"iob":0.222,"activity":0.0052,"bolussnooze":0,"basaliob":0.222,"netbasalinsulin":0.15,"hightempinsulin":0.95,"time":"2017-09-09T11:19:26.000Z"},{"iob":0.197,"activity":0.0051,"bolussnooze":0,"basaliob":0.197,"netbasalinsulin":0.2,"hightempinsulin":0.95,"time":"2017-09-09T11:24:26.000Z"},{"iob":0.172,"activity":0.005,"bolussnooze":0,"basaliob":0.172,"netbasalinsulin":0.3,"hightempinsulin":0.95,"time":"2017-09-09T11:29:26.000Z"},{"iob":0.148,"activity":0.0048,"bolussnooze":0,"basaliob":0.148,"netbasalinsulin":0.35,"hightempinsulin":0.95,"time":"2017-09-09T11:34:26.000Z"},{"iob":0.125,"activity":0.0046,"bolussnooze":0,"basaliob":0.125,"netbasalinsulin":0.45,"hightempinsulin":0.95,"time":"2017-09-09T11:39:26.000Z"},{"iob":0.104,"activity":0.0043,"bolussnooze":0,"basaliob":0.104,"netbasalinsulin":0.55,"hightempinsulin":0.95,"time":"2017-09-09T11:44:26.000Z"},{"iob":0.084,"activity":0.004,"bolussnooze":0,"basaliob":0.084,"netbasalinsulin":0.65,"hightempinsulin":0.95,"time":"2017-09-09T11:49:26.000Z"},{"iob":0.066,"activity":0.0036,"bolussnooze":0,"basaliob":0.066,"netbasalinsulin":0.7,"hightempinsulin":0.95,"time":"2017-09-09T11:54:26.000Z"},{"iob":0.05,"activity":0.0032,"bolussnooze":0,"basaliob":0.05,"netbasalinsulin":0.8,"hightempinsulin":0.95,"time":"2017-09-09T11:59:26.000Z"},{"iob":0.036,"activity":0.0028,"bolussnooze":0,"basaliob":0.036,"netbasalinsulin":0.9,"hightempinsulin":0.95,"time":"2017-09-09T12:04:26.000Z"},{"iob":0.024,"activity":0.0023,"bolussnooze":0,"basaliob":0.024,"netbasalinsulin":0.95,"hightempinsulin":0.95,"time":"2017-09-09T12:09:26.000Z"},{"iob":0.015,"activity":0.0018,"bolussnooze":0,"basaliob":0.015,"netbasalinsulin":0.95,"hightempinsulin":0.95,"time":"2017-09-09T12:14:26.000Z"},{"iob":0.009,"activity":0.0013,"bolussnooze":0,"basaliob":0.009,"netbasalinsulin":0.9,"hightempinsulin":0.9,"time":"2017-09-09T12:19:26.000Z"},{"iob":0.004,"activity":0.0009,"bolussnooze":0,"basaliob":0.004,"netbasalinsulin":0.7,"hightempinsulin":0.7,"time":"2017-09-09T12:24:26.000Z"},{"iob":0.002,"activity":0.0005,"bolussnooze":0,"basaliob":0.002,"netbasalinsulin":0.55,"hightempinsulin":0.55,"time":"2017-09-09T12:29:26.000Z"},{"iob":0.001,"activity":0.0003,"bolussnooze":0,"basaliob":0.001,"netbasalinsulin":0.4,"hightempinsulin":0.4,"time":"2017-09-09T12:34:26.000Z"},{"iob":0,"activity":0.0001,"bolussnooze":0,"basaliob":0,"netbasalinsulin":0.25,"hightempinsulin":0.25,"time":"2017-09-09T12:39:26.000Z"},{"iob":0,"activity":0,"bolussnooze":0,"basaliob":0,"netbasalinsulin":0.1,"hightempinsulin":0.1,"time":"2017-09-09T12:44:26.000Z"},{"iob":0,"activity":0,"bolussnooze":0,"basaliob":0,"netbasalinsulin":0,"hightempinsulin":0,"time":"2017-09-09T12:49:26.000Z"},{"iob":0,"activity":0,"bolussnooze":0,"basaliob":0,"netbasalinsulin":0,"hightempinsulin":0,"time":"2017-09-09T12:54:26.000Z"},{"iob":0,"activity":0,"bolussnooze":0,"basaliob":0,"netbasalinsulin":0,"hightempinsulin":0,"time":"2017-09-09T12:59:26.000Z"}]
