{
  "bg": 132, 
  "temp": "absolute", 
  "snoozeBG": 101, 
  "recieved": true, 
  "predBGs": {
    "IOB": [
      132, 
      130, 
      128, 
      126, 
      124, 
      122, 
      120, 
      118, 
      116, 
      114, 
      112, 
      111, 
      110, 
      109, 
      108, 
      108, 
      107, 
      107, 
      108, 
      108, 
      109, 
      109, 
      110, 
      111, 
      112, 
      113, 
      114, 
      115, 
      116, 
      117, 
      118, 
      119, 
      119, 
      120, 
      120, 
      120, 
      121
    ]
  }, 
  "rate": 0.75, 
  "reason": "COB: 0, Dev: 8, BGI: -2.94, ISF: 95, Target: 100; Eventual BG 101 >= 100, temp 0<0.75U/hr. Setting neutral temp basal of 0.75U/hr", 
  "COB": 0, 
  "eventualBG": 101, 
  "timestamp": "2017-07-31T02:03:54.971323", 
  "duration": 30, 
  "tick": "+0", 
  "IOB": 0.412
}