{
  "bg": 154, 
  "temp": "absolute", 
  "snoozeBG": 101, 
  "recieved": true, 
  "predBGs": {
    "IOB": [
      154, 
      150, 
      146, 
      142, 
      139, 
      135, 
      132, 
      129, 
      126, 
      123, 
      120, 
      117, 
      114, 
      111, 
      109, 
      106, 
      103, 
      101, 
      99, 
      97, 
      95, 
      93, 
      91, 
      90, 
      88, 
      87, 
      86, 
      85, 
      84, 
      84, 
      83, 
      82, 
      82, 
      82, 
      81
    ]
  }, 
  "rate": 0.775, 
  "reason": "COB: 0, Dev: 6, BGI: -4.99, ISF: 95, Target: 80; Eventual BG 101 >= 80, 27m@0.425 = 0.191 > req 0.08+20%. Setting temp basal of 0.775U/hr", 
  "COB": 0, 
  "eventualBG": 101, 
  "timestamp": "2017-08-05T08:17:04.793820", 
  "duration": 30, 
  "tick": -4, 
  "IOB": 0.625
}