{
  "bg": 73, 
  "temp": "absolute", 
  "snoozeBG": 72, 
  "recieved": true, 
  "predBGs": {
    "COB": [
      73, 
      71, 
      70, 
      68, 
      68, 
      68, 
      68, 
      69, 
      71, 
      72, 
      74, 
      76, 
      79, 
      82, 
      84, 
      87, 
      91, 
      94, 
      97, 
      101, 
      104, 
      108, 
      111, 
      115, 
      118, 
      121, 
      125, 
      128, 
      131, 
      134, 
      138, 
      141, 
      144, 
      147, 
      150, 
      153, 
      157, 
      160, 
      163, 
      166, 
      169, 
      171, 
      174
    ], 
    "aCOB": [
      73, 
      77, 
      81, 
      86, 
      91, 
      96, 
      102, 
      108, 
      114, 
      120, 
      127, 
      133, 
      140, 
      147, 
      154, 
      161, 
      168, 
      175, 
      182, 
      189, 
      196, 
      202, 
      209, 
      215, 
      221, 
      227, 
      233, 
      239, 
      244, 
      249, 
      255, 
      260, 
      264, 
      269, 
      274, 
      278, 
      282, 
      286, 
      290, 
      294, 
      297, 
      301, 
      304
    ], 
    "IOB": [
      73, 
      71, 
      69, 
      67, 
      65, 
      63, 
      62, 
      61, 
      60, 
      58, 
      57, 
      56, 
      55, 
      54, 
      53, 
      53, 
      52
    ]
  }, 
  "rate": 0.0, 
  "reason": "COB: 33, Dev: 7, BGI: -5.98, ISF: 90, Target: 100; BG 73<75", 
  "COB": 33, 
  "eventualBG": 174, 
  "timestamp": "2017-09-20T01:25:26.149492", 
  "duration": 30, 
  "tick": -4, 
  "IOB": 0.415
}